treecat/__init__.py
treecat/__main__.py
treecat/_version.py
treecat/treecat.py
treecat-0.4.0.data/scripts/tcat
treecat-0.4.0.dist-info/LICENSE
treecat-0.4.0.dist-info/METADATA
treecat-0.4.0.dist-info/WHEEL
treecat-0.4.0.dist-info/top_level.txt
treecat-0.4.0.dist-info/RECORD
