Metadata-Version: 2.1
Name: treecat
Version: 0.4.0
Summary: Displays a tree view of files and their contents
Home-page: https://github.com/Knio/treecat
Author: Tom Flanagan
Author-email: tom@zkpq.ca
License: MIT
Keywords: tool file
Platform: UNKNOWN
Classifier: Environment :: Console
Classifier: Intended Audience :: Developers
Classifier: Intended Audience :: System Administrators
Classifier: Intended Audience :: End Users/Desktop
Classifier: License :: OSI Approved :: MIT License
Classifier: Operating System :: OS Independent
Classifier: Programming Language :: Python
Classifier: Programming Language :: Python :: 3
Classifier: Topic :: Desktop Environment :: File Managers
Classifier: Topic :: System :: Filesystems
Classifier: Topic :: Utilities
Requires-Dist: colorama
